odoo/addons/base_view_inheritance_extension/README.rst
odoo/addons/base_view_inheritance_extension/__init__.py
odoo/addons/base_view_inheritance_extension/__manifest__.py
odoo/addons/base_view_inheritance_extension/demo/ir_ui_view.xml
odoo/addons/base_view_inheritance_extension/i18n/base_view_inheritance_extension.pot
odoo/addons/base_view_inheritance_extension/i18n/ca.po
odoo/addons/base_view_inheritance_extension/i18n/de.po
odoo/addons/base_view_inheritance_extension/i18n/es.po
odoo/addons/base_view_inheritance_extension/i18n/es_AR.po
odoo/addons/base_view_inheritance_extension/i18n/hr.po
odoo/addons/base_view_inheritance_extension/i18n/it.po
odoo/addons/base_view_inheritance_extension/i18n/nl.po
odoo/addons/base_view_inheritance_extension/i18n/sl.po
odoo/addons/base_view_inheritance_extension/i18n/tr.po
odoo/addons/base_view_inheritance_extension/models/__init__.py
odoo/addons/base_view_inheritance_extension/models/ir_ui_view.py
odoo/addons/base_view_inheritance_extension/readme/CONTRIBUTORS.md
odoo/addons/base_view_inheritance_extension/readme/DESCRIPTION.md
odoo/addons/base_view_inheritance_extension/readme/ROADMAP.md
odoo/addons/base_view_inheritance_extension/readme/USAGE.md
odoo/addons/base_view_inheritance_extension/static/description/icon.png
odoo/addons/base_view_inheritance_extension/static/description/index.html
odoo/addons/base_view_inheritance_extension/tests/__init__.py
odoo/addons/base_view_inheritance_extension/tests/test_base_view_inheritance_extension.py
odoo_addon_base_view_inheritance_extension-19.0.1.0.0.7.dist-info/METADATA
odoo_addon_base_view_inheritance_extension-19.0.1.0.0.7.dist-info/WHEEL
odoo_addon_base_view_inheritance_extension-19.0.1.0.0.7.dist-info/top_level.txt
odoo_addon_base_view_inheritance_extension-19.0.1.0.0.7.dist-info/RECORD
