Metadata-Version: 2.1
Name: odoo-addon-base_view_inheritance_extension
Version: 19.0.1.0.0.7
Requires-Dist: odoo==19.0.*
Summary: Adds more operators for view inheritance
Home-page: https://github.com/OCA/server-tools
License: LGPL-3
Author: Therp BV,Odoo Community Association (OCA)
Author-email: support@odoo-community.org
Classifier: Programming Language :: Python
Classifier: Framework :: Odoo
Classifier: Framework :: Odoo :: 19.0
Classifier: License :: OSI Approved :: GNU Lesser General Public License v3 (LGPLv3)
Classifier: Development Status :: 6 - Mature
